semantix_genai_inference/__init__.py
semantix_genai_inference/cli.py
semantix_genai_inference/inference/__init__.py
semantix_genai_inference/inference/llm/__init__.py
semantix_genai_inference/inference/llm/alpaca.py
semantix_genai_inference/inference/llm/azure_openai.py
semantix_genai_inference/inference/llm/cohere.py
semantix_genai_inference/inference/llm/llama2.py
semantix_genai_inference/inference/llm/openai.py
semantix_genai_inference/inference/model_client.py
semantix_genai_inference-0.0.11.dist-info/entry_points.txt
semantix_genai_inference-0.0.11.dist-info/LICENSE.txt
semantix_genai_inference-0.0.11.dist-info/WHEEL
semantix_genai_inference-0.0.11.dist-info/METADATA
semantix_genai_inference-0.0.11.dist-info/RECORD
