Metadata-Version: 2.1
Name: semantix-genai-inference
Version: 0.0.11
Summary: 
Author: Dev Team
Author-email: dev@semantix.ai
Requires-Python: >=3.8
Classifier: Programming Language :: Python :: 3
Classifier: Programming Language :: Python :: 3.8
Classifier: Programming Language :: Python :: 3.9
Classifier: Programming Language :: Python :: 3.10
Classifier: Programming Language :: Python :: 3.11
Requires-Dist: aiohttp (>=3.8.4,<4.0.0)
Requires-Dist: click (>=8.1.4,<9.0.0)
Requires-Dist: pyyaml (>=6.0.1,<7.0.0)
